Verilog/multiplier.v
module multiplier(a0,a1,a2,a3,b0,b1,b2,b3,p0,p1,p2,p3,p4,p5,p6,c);

    input a0;
    input a1;
    input a2;
    input a3;
    input b0;
    input b1;
    input b2;
    input b3;
    output p0;
    output p1;
    output p2;
    output p3;
    output p4;
    output p5;
    output p6;
    output c;

    and(p0,a0,b0);
    and(o0,a0,b1);
    and(o1,a1,b0);
    and(o2,b2,a0);
    and(o3,a2,b0);
    and(o4,a1,b1);
    and(o5,a1,b2);
    and(o6,a0,b3);
    and(o7,a3,b0);
    and(o8,a2,b1);
    and(o9,a2,b2);
    and(o10,a3,b1);
    and(o11,a1,b3);
    and(o12,a2,b3);
    and(o13,a3,b2);
    and(o14,a3,b3);

    xor(p1,o0,o1);
    and(c0,o0,o1);
    xor(s0,o3,o4);
    and(c2,o3,o4);
    xor(s1,o7,o8);
    and(c3,o7,o8);
    xor(p4,s4,c5);
    and(c8,s4,c5);

    xor(p2,c0,o2,s0);
    xor(y1,c0,o2);
    and(y2,c0,o2);
    and(y3,y1,s0);
    or(c1,y2,y3);
    xor(s2,s1,o5,c2);
    xor(y4,s1,o5);
    and(y5,s1,o5);
    and(y6,y4,s2);
    or(c4,y5,y6);
    xor(p3,o6,c1,s2);
    xor(y7,o6,c1);
    and(y8,o6,c1);
    and(y9,y7,s2);
    or(c5,y8,y9);
    xor(s3,c3,o9,o10);
    xor(y10,c3,o9);
    and(y11,c3,o9);
    and(y12,y10,o10);
    or(c6,y11,y12);
    xor(s4,s3,c4,o11);
    xor(y13,s3,c4);
    and(y14,s3,c4);
    and(y15,y13,o11);
    or(c7,y14,y15);
    xor(s5,o13,o12,c6);
    xor(y16,o13,o12);
    and(y17,o13,o12);
    and(y18,y16,c6);
    or(c9,y17,y18);
    xor(p5,c7,c8,s5);
    xor(y19,c7,c8);
    and(y20,c7,c8);
    and(y21,y19,s5);
    or(c10,y20,y21);
    xor(p6,o14,c9,c10);
    xor(y22,o14,c9);
    and(y23,o14,c9);
    and(y24,y22,c10);
    or(c,y23,y24);

endmodule

Verilog/multiplier_tb.v
`timescale 10ns/100ps

module multiplier_tb;

reg a0,a1,a2,a3,b0,b1,b2,b3;
wire p0,p1,p2,p3,p4,p5,p6,c;

multiplier UUT(a0,a1,a2,a3,b0,b1,b2,b3,p0,p1,p2,p3,p4,p5,p6,c);

initial
    begin
        $dumpfile("multiplier_tb.vcd");
        $dumpvars(0,multiplier_tb);

        a0 = 0;
        a1 = 0;
        a2 = 0;
        a3 = 0;
        b0 = 0;
        b1 = 0;
        b2 = 0;
        b3 = 0;
    end

initial 
begin
     #1
     a0 = 1;
     a1 = 0;
     a2 = 1;
     a3 = 0;
     b0 = 1;
     b1 = 0;
     b2 = 1;
     b3 = 0;

     #1
     a0 = 0;
     a1 = 1;
     a2 = 0;
     a3 = 1;
     b0 = 0;
     b1 = 1;
     b2 = 0;
     b3 = 1;

     #1
     a0 = 1;
     a1 = 0;
     a2 = 0;
     a3 = 1;
     b0 = 1;
     b1 = 0;
     b2 = 0;
     b3 = 1;

     #1
     a0 = 0;
     a1 = 1;
     a2 = 1;
     a3 = 0;
     b0 = 0;
     b1 = 1;
     b2 = 1;
     b3 = 0;

     #1
     a0 = 0;
     a1 = 1;
     a2 = 1;
     a3 = 0;
     b0 = 1;
     b1 = 0;
     b2 = 0;
     b3 = 1;

     #1
     a0 = 0;
     a1 = 1;
     a2 = 0;
     a3 = 1;
     b0 = 1;
     b1 = 0;
     b2 = 0;
     b3 = 1;

     #1
     a0 = 1;
     a1 = 1;
     a2 = 0;
     a3 = 0;
     b0 = 0;
     b1 = 1;
     b2 = 0;
     b3 = 0;

      #1
     a0 = 0;
     a1 = 0;
     a2 = 1;
     a3 = 1;
     b0 = 0;
     b1 = 1;
     b2 = 1;
     b3 = 1;

      #1
     a0 = 1;
     a1 = 1;
     a2 = 1;
     a3 = 1;
     b0 = 1;
     b1 = 1;
     b2 = 1;
     b3 = 1;

      #1
     a0 = 0;
     a1 = 0;
     a2 = 0;
     a3 = 0;
     b0 = 0;
     b1 = 0;
     b2 = 0;
     b3 = 0;
    
end

endmodule

Verilog/multiplier_tb.vcd
$date
	Mon Nov 21 17:07:20 2022
$end
$version
	Icarus Verilog
$end
$timescale
	100ps
$end
$scope module multiplier_tb $end
$var wire 1 ! p6 $end
$var wire 1 " p5 $end
$var wire 1 # p4 $end
$var wire 1 $ p3 $end
$var wire 1 % p2 $end
$var wire 1 & p1 $end
$var wire 1 ' p0 $end
$var wire 1 ( c $end
$var reg 1 ) a0 $end
$var reg 1 * a1 $end
$var reg 1 + a2 $end
$var reg 1 , a3 $end
$var reg 1 - b0 $end
$var reg 1 . b1 $end
$var reg 1 / b2 $end
$var reg 1 0 b3 $end
$scope module UUT $end
$var wire 1 ) a0 $end
$var wire 1 * a1 $end
$var wire 1 + a2 $end
$var wire 1 , a3 $end
$var wire 1 - b0 $end
$var wire 1 . b1 $end
$var wire 1 / b2 $end
$var wire 1 0 b3 $end
$var wire 1 ( c $end
$var wire 1 1 c0 $end
$var wire 1 2 c1 $end
$var wire 1 3 c10 $end
$var wire 1 4 c2 $end
$var wire 1 5 c3 $end
$var wire 1 6 c4 $end
$var wire 1 7 c5 $end
$var wire 1 8 c6 $end
$var wire 1 9 c7 $end
$var wire 1 : c8 $end
$var wire 1 ; c9 $end
$var wire 1 < o0 $end
$var wire 1 = o1 $end
$var wire 1 > o10 $end
$var wire 1 ? o11 $end
$var wire 1 @ o12 $end
$var wire 1 A o13 $end
$var wire 1 B o14 $end
$var wire 1 C o2 $end
$var wire 1 D o3 $end
$var wire 1 E o4 $end
$var wire 1 F o5 $end
$var wire 1 G o6 $end
$var wire 1 H o7 $end
$var wire 1 I o8 $end
$var wire 1 J o9 $end
$var wire 1 ' p0 $end
$var wire 1 & p1 $end
$var wire 1 % p2 $end
$var wire 1 $ p3 $end
$var wire 1 # p4 $end
$var wire 1 " p5 $end
$var wire 1 ! p6 $end
$var wire 1 K s0 $end
$var wire 1 L s1 $end
$var wire 1 M s2 $end
$var wire 1 N s3 $end
$var wire 1 O s4 $end
$var wire 1 P s5 $end
$var wire 1 Q y1 $end
$var wire 1 R y10 $end
$var wire 1 S y11 $end
$var wire 1 T y12 $end
$var wire 1 U y13 $end
$var wire 1 V y14 $end
$var wire 1 W y15 $end
$var wire 1 X y16 $end
$var wire 1 Y y17 $end
$var wire 1 Z y18 $end
$var wire 1 [ y19 $end
$var wire 1 \ y2 $end
$var wire 1 ] y20 $end
$var wire 1 ^ y21 $end
$var wire 1 _ y22 $end
$var wire 1 ` y23 $end
$var wire 1 a y24 $end
$var wire 1 b y3 $end
$var wire 1 c y4 $end
$var wire 1 d y5 $end
$var wire 1 e y6 $end
$var wire 1 f y7 $end
$var wire 1 g y8 $end
$var wire 1 h y9 $end
$upscope $end
$upscope $end
$enddefinitions $end
#0
$dumpvars
0h
0g
0f
0e
0d
0c
0b
0a
0`
0_
0^
0]
0\
0[
0Z
0Y
0X
0W
0V
0U
0T
0S
0R
0Q
0P
0O
0N
0M
0L
0K
0J
0I
0H
0G
0F
0E
0D
0C
0B
0A
0@
0?
0>
0=
0<
0;
0:
09
08
07
06
05
04
03
02
01
00
0/
0.
0-
0,
0+
0*
0)
0(
0'
0&
0%
0$
0#
0"
0!
$end
#100
1$
1f
1#
12
1O
1U
1b
1K
1N
1R
0%
1Q
1D
1J
1'
1C
1/
1-
1+
1)
#200
0$
0f
1"
1[
02
0#
19
0b
1!
1_
0R
0O
1W
1%
0Q
1>
1B
0D
0J
1E
1?
0'
0C
10
0/
1.
0-
1,
0+
1*
0)
#300
1:
17
16
1h
1e
1"
1[
1U
1M
1c
0%
0#
09
0N
1L
0K
1O
0W
0$
1f
0>
1H
0E
0?
1'
1G
0.
1-
0*
1)
#400
0:
19
07
0O
0U
1V
1%
0e
0h
0!
0_
1N
1R
1K
0M
0c
1d
0$
0f
0H
0B
1I
1J
1E
1F
0'
0G
00
1/
1.
0-
0,
1+
1*
0)
#500
0!
1#
0[
03
1O
0W
09
1"
0^
06
0U
0V
1P
1X
0d
0N
0R
0L
1&
1?
1@
0F
0J
0E
0I
1=
1D
10
0/
0.
1-
#600
1[
19
0#
1W
0O
1U
16
1$
1e
1M
1c
0%
1"
1L
1!
1_
0K
0P
0X
1H
1B
0D
0@
1,
0+
#700
0U
06
0"
0[
0$
0e
0#
09
1%
0M
0c
0O
0W
1K
0L
0!
0_
0?
1E
0=
0H
0B
1<
00
1.
0-
0,
1)
#800
1#
1O
1U
1"
16
1(
1P
1$
1e
1`
18
1M
1c
1;
0%
1T
0!
0_
1L
1R
1Y
0K
0&
1>
1A
1B
1I
1J
1@
0E
0<
10
1/
1,
1+
0*
0)
#900
1!
13
17
1^
1g
0T
06
0"
1[
12
1N
0R
1S
0e
1#
19
1\
0L
15
14
0M
1c
0d
0O
1W
11
0%
0Q
0$
0f
1D
1H
1=
1E
1F
1?
1'
1<
1C
1G
1-
1*
1)
#1000
0#
03
0^
0U
0P
0"
0[
0a
0(
0N
08
0;
09
02
0h
07
0!
0_
0`
05
0R
0S
0Y
04
0M
0c
0O
0W
01
0%
0Q
0\
0$
0f
0g
0H
0>
0A
0B
0D
0I
0J
0@
0=
0E
0F
0?
0'
0<
0C
0G
00
0/
0.
0-
0,
0+
0*
0)
